{
	"name" : "clipone",
	"title":"Clip-One",
	"version" : "1.4.0",
	"author" : {
		"name" : "ClipTheme",
		"website" : "http://www.cliptheme.com/"
	},
	"homepage" : "http://www.cliptheme.com/admin-template-clip-one/",
	"use":{
		"npm":{
			"package":"package.json"	
		},
		"typescript":{
			
		}
	},
	"assets" : [
		{"type":"package","name":"jquery"},
		{"type":"package","name":"jquery-ui"},
		{"type":"package","name":"bootstrap"},
		{"type":"package","name":"bootstrap-rtl"},
		{"type":"package","name":"font-awesome"},
		{"type":"package","name":"clipboard"},
		{"type":"package","name":"jquery-bootstrap-checkbox"},
		{"type":"package","name":"jquery-validation"},
		{"type":"package","name":"malihu-custom-scrollbar-plugin"},
		{"type":"package","name":"jquery-mousewheel"},
		{"type":"package","name":"jquery-autosize"},
		{"type":"package","name":"jquery.cookie"},
		{"type":"package","name":"jquery.growl"},
		{"type":"package","name":"jschr-bootstrap-modal"},
		{"type":"package","name":"select2"},
		{"type":"package","name":"webuilder"},
		{"type":"package","name":"bootstrap-inputmsg"},
		{"type":"package","name":"bootstrap-avatar-preview"},
		{"type":"less","file":"node_modules/bootstrap/less/bootstrap.less"},
		{"type":"less","file":"node_modules/bootstrap-rtl/less/bootstrap-rtl.less"},
		{"type":"less","file":"node_modules/font-awesome/less/font-awesome.less"},
		{"type":"css","file":"node_modules/jquery.growl/stylesheets/jquery.growl.css"},
		{"type":"css","file":"node_modules/jquery-ui/themes/base/all.css"},
		{"type":"css","file":"node_modules/jschr-bootstrap-modal/css/bootstrap-modal-bs3patch.css"},
		{"type":"css","file":"node_modules/jschr-bootstrap-modal/css/bootstrap-modal.css"},
		{"type":"css","file":"node_modules/malihu-custom-scrollbar-plugin/jquery.mCustomScrollbar.css"},
		{"type":"less","file":"node_modules/jquery-bootstrap-checkbox/jquery-bootstrap-checkbox.less"},
		{"type":"less", "file":"node_modules/bootstrap-avatar-preview/avatarPreview.less"},
		{"type":"less","file":"assets/less/main.less"},
		{"type":"ts","file":"assets/ts/pages/Main.ts"}

	],
	"autoload":"autoloader.json",
	"languages":{
		"fa_IR" : "langs/fa_IR.json"
	},
	"events": [
		{
			"name":"\\themes\\clipone\\events\\navigation\\build",
			"listener": "listeners\\navigation@removeSettings"
		}
	],
	"views":[
		{
			"name":"\\themes\\clipone\\views\\login",
			"parent":"\\packages\\userpanel\\views\\login",
			"file":"login.php"
		},
		{
			"name":"\\themes\\clipone\\views\\dashboard",
			"parent":"\\packages\\userpanel\\views\\dashboard",
			"file":"dashboard.php"
		},
		{
			"name":"\\themes\\clipone\\views\\users\\listview",
			"parent":"\\packages\\userpanel\\views\\users\\listview",
			"file":"users.list.php"
		},
		{
			"name":"\\themes\\clipone\\views\\users\\add",
			"parent":"\\packages\\userpanel\\views\\users\\add",
			"file":"html/users/add.php"
		},
		{
			"name":"\\themes\\clipone\\views\\users\\edit",
			"parent":"\\packages\\userpanel\\views\\users\\edit",
			"file":"html/users/edit.php"
		},
		{
			"name":"\\themes\\clipone\\views\\users\\view",
			"parent":"\\packages\\userpanel\\views\\users\\view",
			"file":"html/users/view.php"
		},
		{
			"name":"\\themes\\clipone\\views\\users\\delete",
			"parent":"\\packages\\userpanel\\views\\users\\delete",
			"file":"users.delete.php"
		},
		{
			"name":"\\themes\\clipone\\views\\register",
			"parent":"\\packages\\userpanel\\views\\register",
			"file":"register.php"
		},
		{
			"name":"\\themes\\clipone\\views\\lock",
			"parent":"\\packages\\userpanel\\views\\lock",
			"file":"lock.php"
		},
		{
			"name":"\\themes\\clipone\\views\\notfound",
			"parent":"\\packages\\userpanel\\views\\notfound",
			"file":"notfound.php"
		},
		{
			"name":"\\themes\\clipone\\views\\forbidden",
			"parent":"\\packages\\userpanel\\views\\forbidden",
			"file":"forbidden.php"
		},
		{
			"name":"\\themes\\clipone\\views\\settings\\usertypes\\listview",
			"parent":"\\packages\\userpanel\\views\\settings\\usertypes\\listview",
			"file":"settings.usertypes.list.php"
		},
		{
			"name":"\\themes\\clipone\\views\\settings\\usertypes\\edit",
			"parent":"\\packages\\userpanel\\views\\settings\\usertypes\\edit",
			"file":"settings.usertypes.edit.php"
		},
		{
			"name":"\\themes\\clipone\\views\\settings\\usertypes\\delete",
			"parent":"\\packages\\userpanel\\views\\settings\\usertypes\\delete",
			"file":"settings.usertypes.delete.php"
		},
		{
			"name":"\\themes\\clipone\\views\\settings\\usertypes\\add",
			"parent":"\\packages\\userpanel\\views\\settings\\usertypes\\add",
			"file":"settings.usertypes.add.php"
		},
		{
			"name":"\\themes\\clipone\\views\\profile\\view",
			"parent":"\\packages\\userpanel\\views\\profile\\view",
			"file":"html/profile/view.php"
		},
		{
			"name":"\\themes\\clipone\\views\\profile\\edit",
			"parent":"\\packages\\userpanel\\views\\profile\\edit",
			"file":"html/profile/edit.php"
		},
		{
			"name":"\\themes\\clipone\\views\\search",
			"parent":"\\packages\\userpanel\\views\\search",
			"file":"search.php"
		},
		{
			"name":"\\themes\\clipone\\views\\resetpwd",
			"parent":"\\packages\\userpanel\\views\\resetpwd",
			"file":"html/resetpwd.php"
		},
		{
			"name":"\\themes\\clipone\\views\\resetpwd\\newpwd",
			"parent":"\\packages\\userpanel\\views\\resetpwd\\newpwd",
			"file":"html/newpwd.php"
		}
	]
}
